docx_attach/__init__.py
docx_attach/docx_attachment.py
test/test.py
docx_replace_attach-0.0.5.dist-info/LICENSE
docx_replace_attach-0.0.5.dist-info/METADATA
docx_replace_attach-0.0.5.dist-info/WHEEL
docx_replace_attach-0.0.5.dist-info/top_level.txt
docx_replace_attach-0.0.5.dist-info/RECORD
