Metadata-Version: 2.1
Name: docx-replace-attach
Version: 0.0.5
Summary: Replace key words to attachments inside a document of MS Word or Excel
Author-email: mintya <931108724@qq.com>
License: MIT
Project-URL: Homepage, https://github.com/mintya/docx-replace-attach
Classifier: Programming Language :: Python :: 3
Classifier: License :: OSI Approved :: MIT License
Classifier: Operating System :: OS Independent
Requires-Python: >=3.0
License-File: LICENSE
Requires-Dist: python-docx>=1.1.0
Requires-Dist: pillow>=10.3.0
